{
  "project_info": {
    "project_number": "1012228922352",
    "project_id": "lara-story",
    "storage_bucket": "lara-story.appspot.com"
  },
  "client": [
    {
      "client_info": {
        "mobilesdk_app_id": "1:1012228922352:android:bfebf773bcaee1ffd65b35",
        "android_client_info": {
          "package_name": "com.GamezMonster.Larastory"
        }
      },
      "oauth_client": [
        {
          "client_id": "1012228922352-bcv32s3cr60belpt9lukepj382pookdr.apps.googleusercontent.com",
          "client_type": 3
        }
      ],
      "api_key": [
        {
          "current_key": "AIzaSyB5zIqmD_2ioqVgeQQxKnUaXKjG8-XVYGM"
        }
      ],
      "services": {
        "appinvite_service": {
          "other_platform_oauth_client": [
            {
              "client_id": "1012228922352-bcv32s3cr60belpt9lukepj382pookdr.apps.googleusercontent.com",
              "client_type": 3
            }
          ]
        }
      }
    }
  ],
  "configuration_version": "1"
}